tests/__init__.py
tests/assertion.py
tests/conftest.py
tests/test_download.py
tests/test_get.py
tests/test_post_json.py
tests/test_rsa_envelope.py
tests/test_rsaencryptor.py
tests/test_smencryptor.py
tests/test_upload.py
yop_python_sdk/__init__.py
yop_python_sdk/auth/__init__.py
yop_python_sdk/auth/certloader/__init__.py
yop_python_sdk/auth/certloader/yopcertloader.py
yop_python_sdk/auth/v3signer/__init__.py
yop_python_sdk/auth/v3signer/auth.py
yop_python_sdk/auth/v3signer/credentials.py
yop_python_sdk/client/__init__.py
yop_python_sdk/client/client_config.py
yop_python_sdk/client/yop_client_config.py
yop_python_sdk/client/yopclient.py
yop_python_sdk/security/__init__.py
yop_python_sdk/security/crc64.py
yop_python_sdk/security/crc64_combine.py
yop_python_sdk/security/ecdsa/__init__.py
yop_python_sdk/security/ecdsa/curve.py
yop_python_sdk/security/ecdsa/math.py
yop_python_sdk/security/ecdsa/point.py
yop_python_sdk/security/ecdsa/privateKey.py
yop_python_sdk/security/ecdsa/publicKey.py
yop_python_sdk/security/ecdsa/utils/__init__.py
yop_python_sdk/security/ecdsa/utils/base.py
yop_python_sdk/security/ecdsa/utils/binary.py
yop_python_sdk/security/ecdsa/utils/compatibility.py
yop_python_sdk/security/ecdsa/utils/der.py
yop_python_sdk/security/ecdsa/utils/integer.py
yop_python_sdk/security/encryptor/__init__.py
yop_python_sdk/security/encryptor/encryptor.py
yop_python_sdk/security/encryptor/rsaencryptor.py
yop_python_sdk/security/encryptor/smencryptor.py
yop_python_sdk/security/gmssl/__init__.py
yop_python_sdk/security/gmssl/func.py
yop_python_sdk/security/gmssl/sm2.py
yop_python_sdk/security/gmssl/sm3.py
yop_python_sdk/security/gmssl/sm4.py
yop_python_sdk/security/gmssl/utils.py
yop_python_sdk/utils/__init__.py
yop_python_sdk/utils/yop_cashier_util.py
yop_python_sdk/utils/yop_logger.py
yop_python_sdk/utils/yop_security_utils.py
yop_python_sdk-4.3.0.dist-info/LICENSE
yop_python_sdk-4.3.0.dist-info/METADATA
yop_python_sdk-4.3.0.dist-info/WHEEL
yop_python_sdk-4.3.0.dist-info/top_level.txt
yop_python_sdk-4.3.0.dist-info/RECORD
