Metadata-Version: 2.1
Name: yop-python-sdk
Version: 4.3.0
Summary: YOP SDK based on the YOP Common Runtime
Home-page: https://github.com/yop-platform/yop-python-sdk
Author: YOP Team
Author-email: yop@yeepay.com
License: Apache License
Platform: all
Classifier: Intended Audience :: Developers
Classifier: Operating System :: OS Independent
Classifier: Natural Language :: Chinese (Simplified)
Classifier: Programming Language :: Python
Classifier: Programming Language :: Python :: 2
Classifier: Programming Language :: Python :: 3
Classifier: Programming Language :: Python :: 3.6
Classifier: Programming Language :: Python :: 3.7
Classifier: Programming Language :: Python :: 3.8
Classifier: Programming Language :: Python :: 3.9
Classifier: Programming Language :: Python :: 3.10
Classifier: Programming Language :: Python :: 3.11
Classifier: Topic :: Software Development :: Libraries
License-File: LICENSE
Requires-Dist: crcmod>=1.7
Requires-Dist: future>=0.18.2
Requires-Dist: pycryptodome>=3.14.1
Requires-Dist: pyOpenSSL>=22.0.0
Requires-Dist: python-dateutil>=2.8.2
Requires-Dist: requests-toolbelt>=0.9.1
Requires-Dist: simplejson>=3.17.6
